{
  "${modID}:ExampleCard": {
    "NAME": "Name",
    "DESCRIPTION": "Description. NL Second line.",
    "UPGRADE_DESCRIPTION": "This will automatically be used if the card is upgraded. Remove it if unneeded.",
    "EXTENDED_DESCRIPTION": [
      "You can put more text in here.",
      "If you need to use it for stuff.",
      "Blizzard is a good example for this."
    ]
  },
  "${modID}:Strike": {
    "NAME": "Strike",
    "DESCRIPTION": "Deal !D! damage."
  },
  "${modID}:Defend": {
    "NAME": "Defend",
    "DESCRIPTION": "Gain !B! Block."
  },
  "${modID}:DivergentFist": {
    "NAME": "Divergent Fist",
    "DESCRIPTION": "Deal !D! damage. Apply !D! *divergent_fist*."
  },
  "${modID}:SlaughterDemon": {
    "NAME": "Slaughter Demon",
    "DESCRIPTION": "Deal !D! damage. NL If this is the first Attack played in combat, deal !D! more damage."
  },
  "${modID}:CursedFlow": {
    "NAME": "Cursed Flow",
    "DESCRIPTION": "Gain !B! Block. NL If the last card played was an Attack, gain 4 additional Block."
  },
  "${modID}:MartialArtsMastery": {
    "NAME": "Martial Arts Mastery",
    "DESCRIPTION": "Deal !D! damage. NL Draw 1 card. If it is an Attack, gain [E]."
  },
  "${modID}:BlackFlash": {
    "NAME": "Black Flash",
    "DESCRIPTION": "Deal !D! damage. NL Gain [E] for each Attack played this turn. NL *black_flash* synergy."
  },
  "${modID}:CursedEnergyInfusion": {
    "NAME": "Cursed Energy Infusion",
    "DESCRIPTION": "Upgrade a card in your hand. NL If Black Flash was played this turn, reduce its cost by 1 for the rest of combat."
  }
}